npc_cleanup-0.1.0.dist-info/METADATA
npc_cleanup-0.1.0.dist-info/WHEEL
npc_cleanup/__init__.py
npc_cleanup/__main__.py
npc_cleanup/checksum.py
npc_cleanup/exceptions.py
npc_cleanup/models.py
npc_cleanup/npc.py
npc_cleanup/validation.py
npc_cleanup-0.1.0.dist-info/RECORD
