Metadata-Version: 2.1
Name: npc-cleanup
Version: 0.1.0
Author-Email: Christopher <chrism@alleninstitute.org>
License: MIT
Requires-Python: >=3.9
Requires-Dist: npc-lims>=0.1.110
Requires-Dist: npc-sessions>=0.0.179
Requires-Dist: pydantic>=2.6.0
Requires-Dist: pymongo>=4.6.1
Requires-Dist: click>=8.1.7
